mail_panel/__init__.py
mail_panel/backend.py
mail_panel/conf.py
mail_panel/panels.py
mail_panel/static/debug_toolbar/mail/mail_toolbar.css
mail_panel/static/debug_toolbar/mail/toolbar.mail.js
mail_panel/static/debug_toolbar/mail/trash.png
mail_panel/templates/mail_panel/message_overview.html
mail_panel/templates/mail_panel/panel.html
mail_panel/templates/mail_panel/plain_text_message.html
mail_panel/templates/mail_panel/raw_message.html
mail_panel/urls.py
mail_panel/utils.py
mail_panel/views.py
django_mail_panel-4.1.dist-info/LICENSE
django_mail_panel-4.1.dist-info/METADATA
django_mail_panel-4.1.dist-info/WHEEL
django_mail_panel-4.1.dist-info/RECORD
