Metadata-Version: 2.3
Name: django-mail-panel
Version: 4.1
Summary: A panel for django-debug-toolbar that allows for viewing of recently sent email.
License: Apache Software License
Keywords: django,django-debug-toolbar,mail
Author: Stephen Mitchell
Requires-Python: >=3.9,<4.0
Classifier: Development Status :: 5 - Production/Stable
Classifier: Intended Audience :: Developers
Classifier: License :: OSI Approved :: Apache Software License
Classifier: License :: Other/Proprietary License
Classifier: Natural Language :: English
Classifier: Programming Language :: Python
Classifier: Programming Language :: Python :: 3
Classifier: Programming Language :: Python :: 3.9
Classifier: Programming Language :: Python :: 3.10
Classifier: Programming Language :: Python :: 3.11
Classifier: Programming Language :: Python :: 3.12
Classifier: Programming Language :: Python :: 3.13
Classifier: Topic :: Internet :: WWW/HTTP
Requires-Dist: django-debug-toolbar (==5.2.0)
Project-URL: Homepage, https://github.com/scuml/django-mail-panel
Project-URL: Repository, https://github.com/scuml/django-mail-panel
